{
  "showGettingStartedBanner": true,
  "hasMigratedDailyNoteSettings": false,
  "hasMigratedWeeklyNoteSettings": true,
  "daily": {
    "format": "YYYY-ww-MM-DD-E",
    "template": "zob_config/template/daily.md",
    "folder": "dairy/daily",
    "enabled": true
  },
  "weekly": {
    "format": "gggg-[Week]ww-MM",
    "folder": "dairy/weekly",
    "template": "zob_config/template/weekly.md",
    "enabled": true
  },
  "monthly": {
    "format": "",
    "template": "",
    "folder": "",
    "enabled": false
  },
  "quarterly": {
    "format": "",
    "template": "",
    "folder": "",
    "enabled": false
  },
  "yearly": {
    "format": "",
    "template": "",
    "folder": "",
    "enabled": false
  }
}